{
	"credit": "Made with Blockbench",
	"textures": {
		"0": "resprouted:block/iron_double_candle_holder",
		"particle": "resprouted:block/iron_double_candle_holder"
	},
	"elements": [
		{
			"name": "base",
			"from": [6, 0, 15],
			"to": [10, 4, 16],
			"faces": {
				"north": {"uv": [0, 12, 4, 16], "texture": "#0"},
				"east": {"uv": [3, 12, 4, 16], "texture": "#0"},
				"south": {"uv": [0, 12, 4, 16], "texture": "#0"},
				"west": {"uv": [4, 12, 3, 16], "texture": "#0"},
				"up": {"uv": [0, 15, 4, 16], "texture": "#0"},
				"down": {"uv": [0, 15, 4, 16], "texture": "#0"}
			}
		},
		{
			"name": "stick_1",
			"from": [1.5, 0, 15],
			"to": [7.5, 6, 15],
			"rotation": {"angle": -45, "axis": "y", "origin": [7.5, 2, 15]},
			"faces": {
				"north": {"uv": [9, 0, 15, 6], "texture": "#0"},
				"east": {"uv": [0, 0, 0, 6], "texture": "#0"},
				"south": {"uv": [15, 0, 9, 6], "texture": "#0"},
				"west": {"uv": [0, 0, 0, 6], "texture": "#0"},
				"up": {"uv": [0, 0, 0, 4], "rotation": 270, "texture": "#0"},
				"down": {"uv": [0, 0, 0, 4], "rotation": 90, "texture": "#0"}
			}
		},
		{
			"name": "stick_2",
			"from": [3, 4, 13.5],
			"to": [3, 6, 16.5],
			"rotation": {"angle": -45, "axis": "y", "origin": [7.5, 2, 15]},
			"faces": {
				"east": {"uv": [7, 10, 10, 12], "texture": "#0"},
				"west": {"uv": [7, 10, 10, 12], "texture": "#0"},
				"up": {"uv": [0, 0, 0, 4], "rotation": 270, "texture": "#0"},
				"down": {"uv": [0, 0, 0, 4], "rotation": 90, "texture": "#0"}
			}
		},
		{
			"name": "candle_base_1",
			"from": [2.8, 6, 10.325],
			"to": [5.8, 7, 13.325],
			"rotation": {"angle": 0, "axis": "y", "origin": [7.5, 2, 15]},
			"faces": {
				"north": {"uv": [4, 15, 7, 16], "texture": "#0"},
				"east": {"uv": [4, 15, 7, 16], "texture": "#0"},
				"south": {"uv": [4, 15, 7, 16], "texture": "#0"},
				"west": {"uv": [4, 15, 7, 16], "texture": "#0"},
				"up": {"uv": [4, 13, 7, 16], "rotation": 270, "texture": "#0"},
				"down": {"uv": [4, 13, 7, 16], "rotation": 90, "texture": "#0"}
			}
		},
		{
			"name": "stick_3",
			"from": [8.5, 0, 9],
			"to": [8.5, 6, 15],
			"rotation": {"angle": -45, "axis": "y", "origin": [8.5, 2, 15]},
			"faces": {
				"north": {"uv": [0, 0, 0, 6], "texture": "#0"},
				"east": {"uv": [9, 0, 15, 6], "texture": "#0"},
				"south": {"uv": [0, 0, 0, 6], "texture": "#0"},
				"west": {"uv": [15, 0, 9, 6], "texture": "#0"},
				"up": {"uv": [0, 0, 0, 4], "texture": "#0"},
				"down": {"uv": [0, 0, 0, 4], "texture": "#0"}
			}
		},
		{
			"name": "stick_4",
			"from": [7, 4, 10.5],
			"to": [10, 6, 10.5],
			"rotation": {"angle": -45, "axis": "y", "origin": [8.5, 2, 15]},
			"faces": {
				"north": {"uv": [7, 10, 10, 12], "texture": "#0"},
				"south": {"uv": [7, 10, 10, 12], "texture": "#0"},
				"up": {"uv": [0, 0, 0, 4], "texture": "#0"},
				"down": {"uv": [0, 0, 0, 4], "texture": "#0"}
			}
		},
		{
			"name": "candle_base_2",
			"from": [10.2, 6, 10.325],
			"to": [13.2, 7, 13.325],
			"rotation": {"angle": 0, "axis": "y", "origin": [8.5, 2, 15]},
			"faces": {
				"north": {"uv": [4, 15, 7, 16], "texture": "#0"},
				"east": {"uv": [4, 15, 7, 16], "texture": "#0"},
				"south": {"uv": [4, 15, 7, 16], "texture": "#0"},
				"west": {"uv": [4, 15, 7, 16], "texture": "#0"},
				"up": {"uv": [4, 13, 7, 16], "texture": "#0"},
				"down": {"uv": [4, 13, 7, 16], "texture": "#0"}
			}
		}
	],
	"groups": [
		{
			"name": "group",
			"origin": [0, 0, 0],
			"color": 0,
			"children": [0, 1, 2, 3, 4, 5, 6]
		}
	]
}